AUTHORS
LICENCE
MANIFEST.in
README.md
setup.py
django_naremitcms_docimport.egg-info/PKG-INFO
django_naremitcms_docimport.egg-info/SOURCES.txt
django_naremitcms_docimport.egg-info/dependency_links.txt
django_naremitcms_docimport.egg-info/not-zip-safe
django_naremitcms_docimport.egg-info/top_level.txt
naremitcms_docimport/__init__.py
naremitcms_docimport/docimport.py
naremitcms_docimport/models.py
naremitcms_docimport/management/__init__.py
naremitcms_docimport/management/commands/__init__.py
naremitcms_docimport/management/commands/docimport.py
naremitcms_docimport/migrations/0001_initial.py
naremitcms_docimport/migrations/__init__.py
naremitcms_docimport/templates/naremitcms-docimport/example.html
naremitcms_docimport/templates/naremitcms-docimport/menu.html